.gitignore
CHANGES.rst
MANIFEST.in
README.rst
setup.cfg
setup.py
docs/INSTALL.txt
docs/LICENSE.GPL
docs/LICENSE.txt
plone/__init__.py
plone.mocktestcase.egg-info/PKG-INFO
plone.mocktestcase.egg-info/SOURCES.txt
plone.mocktestcase.egg-info/dependency_links.txt
plone.mocktestcase.egg-info/entry_points.txt
plone.mocktestcase.egg-info/namespace_packages.txt
plone.mocktestcase.egg-info/not-zip-safe
plone.mocktestcase.egg-info/requires.txt
plone.mocktestcase.egg-info/top_level.txt
plone/mocktestcase/__init__.py
plone/mocktestcase/dummy.py
plone/mocktestcase/testcase.py