Metadata-Version: 1.1
Name: plone.mocktestcase
Version: 1.0
Summary: Mock unit test case based on ``mocker``
Home-page: http://plone.org
Author: Martin Aspeli
Author-email: optilude@gmail.com
License: LGPL
Platform: UNKNOWN
Classifier: Framework :: Plone
Classifier: Programming Language :: Python
Classifier: Topic :: Software Development :: Libraries :: Python Modules
